libvxshare/__init__.py
libvxshare/apiv2.py
libvxshare/tests/__init__.py
libvxshare/tests/test_apiv2.py
libvxshare-1.0.0.dist-info/LICENSE
libvxshare-1.0.0.dist-info/METADATA
libvxshare-1.0.0.dist-info/WHEEL
libvxshare-1.0.0.dist-info/top_level.txt
libvxshare-1.0.0.dist-info/RECORD
